README.txt
setup.py
collective/__init__.py
collective.portlet.adsense.egg-info/PKG-INFO
collective.portlet.adsense.egg-info/SOURCES.txt
collective.portlet.adsense.egg-info/dependency_links.txt
collective.portlet.adsense.egg-info/entry_points.txt
collective.portlet.adsense.egg-info/namespace_packages.txt
collective.portlet.adsense.egg-info/not-zip-safe
collective.portlet.adsense.egg-info/paster_plugins.txt
collective.portlet.adsense.egg-info/requires.txt
collective.portlet.adsense.egg-info/top_level.txt
collective/portlet/__init__.py
collective/portlet/adsense/__init__.py
collective/portlet/adsense/adsenseportlet.pt
collective/portlet/adsense/adsenseportlet.py
collective/portlet/adsense/configure.zcml
collective/portlet/adsense/version.txt
collective/portlet/adsense/vocabularies.py
collective/portlet/adsense/profiles/default/metadata.xml
collective/portlet/adsense/profiles/default/portlets.xml
collective/portlet/adsense/tests/__init__.py
collective/portlet/adsense/tests/base.py
collective/portlet/adsense/tests/test_portlet.py
docs/HISTORY.txt
docs/INSTALL.txt
docs/LICENSE.GPL
docs/LICENSE.txt