Metadata-Version: 1.0
Name: collective.portlet.adsense
Version: 0.5
Summary: A portlet for google adsense
Home-page: http://plone.org/products/collective-portlet-adsense
Author: Eleonora Borelli; Francesco Merlo
Author-email: eleonora@reflab.com; francesco.merlo@reflab.com
License: GPL
Platform: UNKNOWN
Classifier: Framework :: Plone
Classifier: Programming Language :: Python
Classifier: Topic :: Software Development :: Libraries :: Python Modules
